{
    "title": "TED Value",
    "print_title": "no",
    "legend": "upper left",
    "legend_font_size": 18,
    "grid": "on",
    "dataset_name": "Python",
    "markers": ["+", "x", "."],
    "colors": ["limegreen", "chocolate", "hotpink"],
    "tables": [
        {
            "table_name": "python_touzetd_x_threshold_y_runtime_sum", 
            "attributes": [
                {
                    "attr_name": "avg(sum_runtime)"
                }
            ],
            "name": "BSM"
        },
        {
            "table_name": "python_labelguided_x_threshold_y_runtime_sum", 
            "attributes": [
                {
                    "attr_name": "avg(sum_runtime)"
                }
            ],
            "name": "LGM"
        }
    ],
    "x_axis": {
        "db_column": "ted_threshold",
        "name": "Threshold", 
        "font_size": 18, 
        "ticks_font_size": 16
    },
    "y_axis": {
        "name": "Runtime [ms]", 
        "font_size": 18, 
        "ticks_font_size": 16
    }
}